libsourcemap/__init__.py
libsourcemap/_compat.py
libsourcemap/_libsourcemap.so
libsourcemap/_sourcemapnative.py
libsourcemap/exceptions.py
libsourcemap/highlevel.py
libsourcemap-0.8.2.dist-info/DESCRIPTION.rst
libsourcemap-0.8.2.dist-info/METADATA
libsourcemap-0.8.2.dist-info/RECORD
libsourcemap-0.8.2.dist-info/WHEEL
libsourcemap-0.8.2.dist-info/metadata.json
libsourcemap-0.8.2.dist-info/top_level.txt
